odoo/addons/account_invoice_line_sale_line_position/README.rst
odoo/addons/account_invoice_line_sale_line_position/__init__.py
odoo/addons/account_invoice_line_sale_line_position/__manifest__.py
odoo/addons/account_invoice_line_sale_line_position/i18n/account_invoice_line_sale_line_position.pot
odoo/addons/account_invoice_line_sale_line_position/i18n/de.po
odoo/addons/account_invoice_line_sale_line_position/i18n/es.po
odoo/addons/account_invoice_line_sale_line_position/i18n/it.po
odoo/addons/account_invoice_line_sale_line_position/i18n/pt_BR.po
odoo/addons/account_invoice_line_sale_line_position/i18n/tr.po
odoo/addons/account_invoice_line_sale_line_position/models/__init__.py
odoo/addons/account_invoice_line_sale_line_position/models/account_invoice.py
odoo/addons/account_invoice_line_sale_line_position/readme/CONTRIBUTORS.md
odoo/addons/account_invoice_line_sale_line_position/readme/CREDITS.md
odoo/addons/account_invoice_line_sale_line_position/readme/DESCRIPTION.md
odoo/addons/account_invoice_line_sale_line_position/report/invoice_report.xml
odoo/addons/account_invoice_line_sale_line_position/static/description/icon.png
odoo/addons/account_invoice_line_sale_line_position/static/description/index.html
odoo/addons/account_invoice_line_sale_line_position/tests/__init__.py
odoo/addons/account_invoice_line_sale_line_position/tests/test_account_invoice_line_sale_line_position.py
odoo/addons/account_invoice_line_sale_line_position/views/account_move_views.xml
odoo_addon_account_invoice_line_sale_line_position-18.0.1.0.1.dist-info/METADATA
odoo_addon_account_invoice_line_sale_line_position-18.0.1.0.1.dist-info/WHEEL
odoo_addon_account_invoice_line_sale_line_position-18.0.1.0.1.dist-info/top_level.txt
odoo_addon_account_invoice_line_sale_line_position-18.0.1.0.1.dist-info/RECORD
